tcCalc3/__init__.py
tcCalc3/calculator.py
tcCalc3-0.0.4.dist-info/LICENSE
tcCalc3-0.0.4.dist-info/METADATA
tcCalc3-0.0.4.dist-info/WHEEL
tcCalc3-0.0.4.dist-info/top_level.txt
tcCalc3-0.0.4.dist-info/RECORD
