Metadata-Version: 2.1
Name: tcCalc3
Version: 0.0.4
Summary: A simple calculator package
Home-page: https://github.com/armymp/calculator
Author: Dennis Paskel
Classifier: Programming Language :: Python :: 3
Classifier: License :: OSI Approved :: MIT License
Classifier: Operating System :: OS Independent
Requires-Python: >=3.6
License-File: LICENSE
